wasd/__init__.py
wasd/__main__.py
wasd/cli/__init__.py
wasd/cli/scaffold.py
wasd/cli/boilerplate/__init__.py.txt
wasd/cli/boilerplate/_wasd_settings.yml.txt
wasd/cli/boilerplate/base_page.py.txt
wasd/cli/boilerplate/config_browsers.json.txt
wasd/cli/boilerplate/env_stable.yml.txt
wasd/cli/boilerplate/home_page.py.txt
wasd/cli/boilerplate/pytest.ini.txt
wasd/cli/boilerplate/requirements.txt
wasd/cli/boilerplate/tasks.py.txt
wasd/cli/boilerplate/tests_conftest.py.txt
wasd/cli/boilerplate/tests_sample.py.txt
wasd/common/__init__.py
wasd/common/exceptions.py
wasd/common/logger.py
wasd/core/__init__.py
wasd/core/fixtures.py
wasd/core/session.py
wasd/core/settings_manager.py
wasd/support/__init__.py
wasd/support/expected_conditions.py
wasd/support/wait.py
wasd/util/__init__.py
wasd/util/locator.py
wasd/wd/__init__.py
wasd/wd/browser.py
wasd/wd/element.py
wasd/wd/listener.py
wasd-1.0.99.dist-info/METADATA
wasd-1.0.99.dist-info/WHEEL
wasd-1.0.99.dist-info/entry_points.txt
wasd-1.0.99.dist-info/top_level.txt
wasd-1.0.99.dist-info/RECORD
