Metadata-Version: 2.1
Name: wasd
Version: 1.0.99
Summary: The Kostyan Selenium Wrapper
Home-page: https://github.com/Aurococcus/wasd
Author: Kostyan Opasnost
Author-email: aurococcus@gmail.com
Maintainer: Kostyan
License: MIT
Platform: UNKNOWN
Requires-Dist: pip (>=20.0.2)
Requires-Dist: setuptools
Requires-Dist: wheel
Requires-Dist: selenium (>=3.141.0)
Requires-Dist: lxml
Requires-Dist: cssselect
Requires-Dist: pyyaml
Requires-Dist: invoke
Requires-Dist: colorlog
Requires-Dist: pyhamcrest
Requires-Dist: termcolor
Requires-Dist: pytest (>=5.3.5) ; python_version >= "3"
